{"abstract":[{"type":"text","text":"An interactive card for displaying routing results, including updating from\/to location, time and selected modes."}],"relationshipsSections":[{"title":"Inherits From","identifiers":["doc:\/\/TripKitUI\/documentation\/TripKitUI\/TKUITableCard"],"type":"inheritsFrom","kind":"relationships"},{"title":"Conforms To","identifiers":["doc:\/\/TripKitUI\/objc(pl)NSObject","doc:\/\/TripKitUI\/7RxSwift18ReactiveCompatibleP","doc:\/\/TripKitUI\/s7CVarArgP","doc:\/\/TripKitUI\/s8CopyableP","doc:\/\/TripKitUI\/s28CustomDebugStringConvertibleP","doc:\/\/TripKitUI\/s23CustomStringConvertibleP","doc:\/\/TripKitUI\/SQ","doc:\/\/TripKitUI\/SH","doc:\/\/TripKitUI\/s8SendableP","doc:\/\/TripKitUI\/s16SendableMetatypeP","doc:\/\/TripKitUI\/20TGCardViewController013TGPreferrableB0P","doc:\/\/TripKitUI\/documentation\/TripKitUI\/TKUIRoutingQueryInputCardDelegate","doc:\/\/TripKitUI\/documentation\/TripKitUI\/TKUITimePickerSheetDelegate","doc:\/\/TripKitUI\/objc(pl)UIActivityItemsConfigurationProviding","doc:\/\/TripKitUI\/objc(pl)UIPasteConfigurationSupporting","doc:\/\/TripKitUI\/objc(pl)UIResponderStandardEditActions","doc:\/\/TripKitUI\/objc(pl)UIScrollViewDelegate","doc:\/\/TripKitUI\/objc(pl)UITableViewDelegate","doc:\/\/TripKitUI\/objc(pl)UIUserActivityRestoring"],"type":"conformsTo","kind":"relationships"}],"seeAlsoSections":[{"title":"Trip Planning Interface","anchor":"Trip-Planning-Interface","identifiers":["doc:\/\/TripKitUI\/documentation\/TripKitUI\/TKUIRoutingResultsViewController","doc:\/\/TripKitUI\/documentation\/TripKitUI\/TKUIRoutingResultsViewControllerDelegate","doc:\/\/TripKitUI\/documentation\/TripKitUI\/TKUIRoutingResultsCardDelegate","doc:\/\/TripKitUI\/documentation\/TripKitUI\/TKUIRoutingQueryInputCard","doc:\/\/TripKitUI\/documentation\/TripKitUI\/TKUIRoutingQueryInputCardDelegate","doc:\/\/TripKitUI\/documentation\/TripKitUI\/TKUITripOverviewViewController","doc:\/\/TripKitUI\/documentation\/TripKitUI\/TKUITripOverviewCard","doc:\/\/TripKitUI\/documentation\/TripKitUI\/TKUITripModeByModeViewController","doc:\/\/TripKitUI\/documentation\/TripKitUI\/TKUITripModeByModeViewControllerDelegate","doc:\/\/TripKitUI\/documentation\/TripKitUI\/TKUITripModeByModeCard","doc:\/\/TripKitUI\/documentation\/TripKitUI\/TKUITripModeByModePageBuilder"],"generated":true}],"hierarchy":{"paths":[["doc:\/\/TripKitUI\/documentation\/TripKitUI"]]},"variants":[{"paths":["\/documentation\/tripkitui\/tkuiroutingresultscard"],"traits":[{"interfaceLanguage":"swift"}]}],"kind":"symbol","topicSections":[{"title":"Structures","anchor":"Structures","identifiers":["doc:\/\/TripKitUI\/documentation\/TripKitUI\/TKUIRoutingResultsCard\/Configuration","doc:\/\/TripKitUI\/documentation\/TripKitUI\/TKUIRoutingResultsCard\/CustomItem"],"generated":true},{"title":"Initializers","anchor":"Initializers","identifiers":["doc:\/\/TripKitUI\/documentation\/TripKitUI\/TKUIRoutingResultsCard\/init(destination:origin:zoomToDestination:initialPosition:)","doc:\/\/TripKitUI\/documentation\/TripKitUI\/TKUIRoutingResultsCard\/init(request:editable:modes:)"],"generated":true},{"title":"Instance Properties","anchor":"Instance-Properties","identifiers":["doc:\/\/TripKitUI\/documentation\/TripKitUI\/TKUIRoutingResultsCard\/keyCommands","doc:\/\/TripKitUI\/documentation\/TripKitUI\/TKUIRoutingResultsCard\/onSelection","doc:\/\/TripKitUI\/documentation\/TripKitUI\/TKUIRoutingResultsCard\/preferredView","doc:\/\/TripKitUI\/documentation\/TripKitUI\/TKUIRoutingResultsCard\/resultsDelegate"],"generated":true},{"title":"Instance Methods","anchor":"Instance-Methods","identifiers":["doc:\/\/TripKitUI\/documentation\/TripKitUI\/TKUIRoutingResultsCard\/canPerformAction(_:withSender:)","doc:\/\/TripKitUI\/documentation\/TripKitUI\/TKUIRoutingResultsCard\/debugActionCopyPrimaryRequest(_:)","doc:\/\/TripKitUI\/documentation\/TripKitUI\/TKUIRoutingResultsCard\/didAppear(animated:)","doc:\/\/TripKitUI\/documentation\/TripKitUI\/TKUIRoutingResultsCard\/didBuild(tableView:cardView:)","doc:\/\/TripKitUI\/documentation\/TripKitUI\/TKUIRoutingResultsCard\/refreshForUpdatedModes()","doc:\/\/TripKitUI\/documentation\/TripKitUI\/TKUIRoutingResultsCard\/traitCollectionDidChange(_:)","doc:\/\/TripKitUI\/documentation\/TripKitUI\/TKUIRoutingResultsCard\/willAppear(animated:)","doc:\/\/TripKitUI\/documentation\/TripKitUI\/TKUIRoutingResultsCard\/willDisappear(animated:)"],"generated":true},{"title":"Type Aliases","anchor":"Type-Aliases","identifiers":["doc:\/\/TripKitUI\/documentation\/TripKitUI\/TKUIRoutingResultsCard\/TripGroupAction"],"generated":true},{"title":"Type Properties","anchor":"Type-Properties","identifiers":["doc:\/\/TripKitUI\/documentation\/TripKitUI\/TKUIRoutingResultsCard\/config"],"generated":true},{"title":"Enumerations","anchor":"Enumerations","identifiers":["doc:\/\/TripKitUI\/documentation\/TripKitUI\/TKUIRoutingResultsCard\/SupportType"],"generated":true},{"title":"Default Implementations","anchor":"Default-Implementations","identifiers":["doc:\/\/TripKitUI\/documentation\/TripKitUI\/TKUIRoutingResultsCard\/TKUIRoutingQueryInputCardDelegate-Implementations","doc:\/\/TripKitUI\/documentation\/TripKitUI\/TKUIRoutingResultsCard\/TKUITimePickerSheetDelegate-Implementations","doc:\/\/TripKitUI\/documentation\/TripKitUI\/TKUIRoutingResultsCard\/UITableViewDelegate-Implementations"],"generated":true}],"primaryContentSections":[{"declarations":[{"tokens":[{"kind":"attribute","text":"@"},{"kind":"attribute","preciseIdentifier":"s:ScM","text":"MainActor"},{"kind":"text","text":" "},{"kind":"keyword","text":"class"},{"kind":"text","text":" "},{"kind":"identifier","text":"TKUIRoutingResultsCard"}],"platforms":["iOS"],"languages":["swift"]}],"kind":"declarations"},{"content":[{"type":"heading","level":2,"anchor":"overview","text":"Overview"},{"type":"paragraph","inlineContent":[{"text":"Can be used standalone or via ","type":"text"},{"isActive":true,"type":"reference","identifier":"doc:\/\/TripKitUI\/documentation\/TripKitUI\/TKUIRoutingResultsViewController"},{"text":".","type":"text"}]}],"kind":"content"}],"metadata":{"fragments":[{"kind":"keyword","text":"class"},{"kind":"text","text":" "},{"kind":"identifier","text":"TKUIRoutingResultsCard"}],"roleHeading":"Class","symbolKind":"class","navigatorTitle":[{"text":"TKUIRoutingResultsCard","kind":"identifier"}],"role":"symbol","title":"TKUIRoutingResultsCard","modules":[{"name":"TripKitUI"}],"externalID":"c:@M@TripKitUI@objc(cs)TKUIRoutingResultsCard"},"schemaVersion":{"minor":3,"major":0,"patch":0},"identifier":{"url":"doc:\/\/TripKitUI\/documentation\/TripKitUI\/TKUIRoutingResultsCard","interfaceLanguage":"swift"},"sections":[],"references":{"doc://TripKitUI/documentation/TripKitUI/TKUITimePickerSheetDelegate":{"title":"TKUITimePickerSheetDelegate","kind":"symbol","type":"topic","abstract":[],"identifier":"doc:\/\/TripKitUI\/documentation\/TripKitUI\/TKUITimePickerSheetDelegate","url":"\/documentation\/tripkitui\/tkuitimepickersheetdelegate","fragments":[{"text":"protocol","kind":"keyword"},{"text":" ","kind":"text"},{"text":"TKUITimePickerSheetDelegate","kind":"identifier"}],"navigatorTitle":[{"text":"TKUITimePickerSheetDelegate","kind":"identifier"}],"role":"symbol"},"doc://TripKitUI/SQ":{"type":"unresolvable","identifier":"doc:\/\/TripKitUI\/SQ","title":"Swift.Equatable"},"doc://TripKitUI/objc(pl)UIPasteConfigurationSupporting":{"title":"UIKit.UIPasteConfigurationSupporting","identifier":"doc:\/\/TripKitUI\/objc(pl)UIPasteConfigurationSupporting","type":"unresolvable"},"doc://TripKitUI/documentation/TripKitUI/TKUITripModeByModePageBuilder":{"type":"topic","role":"symbol","url":"\/documentation\/tripkitui\/tkuitripmodebymodepagebuilder","kind":"symbol","abstract":[],"fragments":[{"kind":"keyword","text":"protocol"},{"kind":"text","text":" "},{"kind":"identifier","text":"TKUITripModeByModePageBuilder"}],"navigatorTitle":[{"kind":"identifier","text":"TKUITripModeByModePageBuilder"}],"identifier":"doc:\/\/TripKitUI\/documentation\/TripKitUI\/TKUITripModeByModePageBuilder","title":"TKUITripModeByModePageBuilder"},"doc://TripKitUI/objc(pl)NSObject":{"type":"unresolvable","identifier":"doc:\/\/TripKitUI\/objc(pl)NSObject","title":"ObjectiveC.NSObjectProtocol"},"doc://TripKitUI/documentation/TripKitUI/TKUIRoutingResultsCard/resultsDelegate":{"abstract":[],"kind":"symbol","fragments":[{"text":"var","kind":"keyword"},{"text":" ","kind":"text"},{"text":"resultsDelegate","kind":"identifier"},{"text":": ","kind":"text"},{"preciseIdentifier":"s:9TripKitUI30TKUIRoutingResultsCardDelegateP","text":"TKUIRoutingResultsCardDelegate","kind":"typeIdentifier"},{"text":"?","kind":"text"}],"role":"symbol","url":"\/documentation\/tripkitui\/tkuiroutingresultscard\/resultsdelegate","identifier":"doc:\/\/TripKitUI\/documentation\/TripKitUI\/TKUIRoutingResultsCard\/resultsDelegate","type":"topic","title":"resultsDelegate"},"doc://TripKitUI/documentation/TripKitUI/TKUIRoutingResultsCard/TKUITimePickerSheetDelegate-Implementations":{"identifier":"doc:\/\/TripKitUI\/documentation\/TripKitUI\/TKUIRoutingResultsCard\/TKUITimePickerSheetDelegate-Implementations","url":"\/documentation\/tripkitui\/tkuiroutingresultscard\/tkuitimepickersheetdelegate-implementations","abstract":[],"type":"topic","kind":"article","role":"collectionGroup","title":"TKUITimePickerSheetDelegate Implementations"},"doc://TripKitUI/documentation/TripKitUI/TKUIRoutingResultsCard/debugActionCopyPrimaryRequest(_:)":{"fragments":[{"text":"func","kind":"keyword"},{"text":" ","kind":"text"},{"text":"debugActionCopyPrimaryRequest","kind":"identifier"},{"text":"(","kind":"text"},{"text":"AnyObject","kind":"typeIdentifier","preciseIdentifier":"s:s9AnyObjecta"},{"text":"?)","kind":"text"}],"identifier":"doc:\/\/TripKitUI\/documentation\/TripKitUI\/TKUIRoutingResultsCard\/debugActionCopyPrimaryRequest(_:)","type":"topic","role":"symbol","kind":"symbol","abstract":[],"title":"debugActionCopyPrimaryRequest(_:)","url":"\/documentation\/tripkitui\/tkuiroutingresultscard\/debugactioncopyprimaryrequest(_:)"},"doc://TripKitUI/documentation/TripKitUI/TKUIRoutingResultsCard/didBuild(tableView:cardView:)":{"abstract":[],"role":"symbol","url":"\/documentation\/tripkitui\/tkuiroutingresultscard\/didbuild(tableview:cardview:)","identifier":"doc:\/\/TripKitUI\/documentation\/TripKitUI\/TKUIRoutingResultsCard\/didBuild(tableView:cardView:)","fragments":[{"text":"func","kind":"keyword"},{"text":" ","kind":"text"},{"text":"didBuild","kind":"identifier"},{"text":"(","kind":"text"},{"text":"tableView","kind":"externalParam"},{"text":": ","kind":"text"},{"preciseIdentifier":"c:objc(cs)UITableView","text":"UITableView","kind":"typeIdentifier"},{"text":", ","kind":"text"},{"text":"cardView","kind":"externalParam"},{"text":": ","kind":"text"},{"preciseIdentifier":"c:@M@TGCardViewController@objc(cs)TGCardView","text":"TGCardView","kind":"typeIdentifier"},{"text":")","kind":"text"}],"type":"topic","title":"didBuild(tableView:cardView:)","kind":"symbol"},"doc://TripKitUI/documentation/TripKitUI/TKUIRoutingResultsCard/UITableViewDelegate-Implementations":{"kind":"article","url":"\/documentation\/tripkitui\/tkuiroutingresultscard\/uitableviewdelegate-implementations","abstract":[],"identifier":"doc:\/\/TripKitUI\/documentation\/TripKitUI\/TKUIRoutingResultsCard\/UITableViewDelegate-Implementations","type":"topic","title":"UITableViewDelegate Implementations","role":"collectionGroup"},"doc://TripKitUI/documentation/TripKitUI/TKUIRoutingResultsCard/SupportType":{"url":"\/documentation\/tripkitui\/tkuiroutingresultscard\/supporttype","type":"topic","kind":"symbol","navigatorTitle":[{"text":"SupportType","kind":"identifier"}],"identifier":"doc:\/\/TripKitUI\/documentation\/TripKitUI\/TKUIRoutingResultsCard\/SupportType","title":"TKUIRoutingResultsCard.SupportType","role":"symbol","abstract":[{"type":"text","text":"Enumeration used when the user taps a button to get help, see "},{"type":"codeVoice","code":"TKUIRoutingResultsCard.Configuration.contactCustomerSupport"}],"fragments":[{"text":"enum","kind":"keyword"},{"text":" ","kind":"text"},{"text":"SupportType","kind":"identifier"}]},"doc://TripKitUI/documentation/TripKitUI/TKUIRoutingQueryInputCard":{"fragments":[{"text":"class","kind":"keyword"},{"text":" ","kind":"text"},{"text":"TKUIRoutingQueryInputCard","kind":"identifier"}],"navigatorTitle":[{"text":"TKUIRoutingQueryInputCard","kind":"identifier"}],"abstract":[{"text":"An interactive card for searching for from and to locations.","type":"text"}],"role":"symbol","type":"topic","kind":"symbol","url":"\/documentation\/tripkitui\/tkuiroutingqueryinputcard","identifier":"doc:\/\/TripKitUI\/documentation\/TripKitUI\/TKUIRoutingQueryInputCard","title":"TKUIRoutingQueryInputCard"},"doc://TripKitUI/documentation/TripKitUI/TKUITripModeByModeViewControllerDelegate":{"url":"\/documentation\/tripkitui\/tkuitripmodebymodeviewcontrollerdelegate","navigatorTitle":[{"kind":"identifier","text":"TKUITripModeByModeViewControllerDelegate"}],"identifier":"doc:\/\/TripKitUI\/documentation\/TripKitUI\/TKUITripModeByModeViewControllerDelegate","type":"topic","role":"symbol","kind":"symbol","abstract":[],"title":"TKUITripModeByModeViewControllerDelegate","fragments":[{"kind":"keyword","text":"protocol"},{"kind":"text","text":" "},{"kind":"identifier","text":"TKUITripModeByModeViewControllerDelegate"}]},"doc://TripKitUI/SH":{"type":"unresolvable","identifier":"doc:\/\/TripKitUI\/SH","title":"Swift.Hashable"},"doc://TripKitUI/documentation/TripKitUI/TKUIRoutingResultsCard/preferredView":{"kind":"symbol","url":"\/documentation\/tripkitui\/tkuiroutingresultscard\/preferredview","abstract":[],"fragments":[{"kind":"keyword","text":"var"},{"kind":"text","text":" "},{"kind":"identifier","text":"preferredView"},{"kind":"text","text":": "},{"kind":"typeIdentifier","preciseIdentifier":"c:objc(cs)UIView","text":"UIView"},{"kind":"text","text":"?"}],"identifier":"doc:\/\/TripKitUI\/documentation\/TripKitUI\/TKUIRoutingResultsCard\/preferredView","type":"topic","title":"preferredView","role":"symbol"},"doc://TripKitUI/s8SendableP":{"type":"unresolvable","identifier":"doc:\/\/TripKitUI\/s8SendableP","title":"Swift.Sendable"},"doc://TripKitUI/documentation/TripKitUI/TKUIRoutingQueryInputCardDelegate":{"kind":"symbol","identifier":"doc:\/\/TripKitUI\/documentation\/TripKitUI\/TKUIRoutingQueryInputCardDelegate","abstract":[],"fragments":[{"text":"protocol","kind":"keyword"},{"text":" ","kind":"text"},{"text":"TKUIRoutingQueryInputCardDelegate","kind":"identifier"}],"type":"topic","role":"symbol","title":"TKUIRoutingQueryInputCardDelegate","navigatorTitle":[{"text":"TKUIRoutingQueryInputCardDelegate","kind":"identifier"}],"url":"\/documentation\/tripkitui\/tkuiroutingqueryinputcarddelegate"},"doc://TripKitUI/documentation/TripKitUI/TKUITableCard":{"fragments":[{"text":"class","kind":"keyword"},{"text":" ","kind":"text"},{"text":"TKUITableCard","kind":"identifier"}],"type":"topic","navigatorTitle":[{"text":"TKUITableCard","kind":"identifier"}],"title":"TKUITableCard","url":"\/documentation\/tripkitui\/tkuitablecard","kind":"symbol","role":"symbol","identifier":"doc:\/\/TripKitUI\/documentation\/TripKitUI\/TKUITableCard","abstract":[]},"doc://TripKitUI/objc(pl)UIActivityItemsConfigurationProviding":{"identifier":"doc:\/\/TripKitUI\/objc(pl)UIActivityItemsConfigurationProviding","type":"unresolvable","title":"UIKit.UIActivityItemsConfigurationProviding"},"doc://TripKitUI/documentation/TripKitUI/TKUITripOverviewCard":{"title":"TKUITripOverviewCard","kind":"symbol","role":"symbol","abstract":[],"identifier":"doc:\/\/TripKitUI\/documentation\/TripKitUI\/TKUITripOverviewCard","type":"topic","navigatorTitle":[{"text":"TKUITripOverviewCard","kind":"identifier"}],"url":"\/documentation\/tripkitui\/tkuitripoverviewcard","fragments":[{"text":"class","kind":"keyword"},{"text":" ","kind":"text"},{"text":"TKUITripOverviewCard","kind":"identifier"}]},"doc://TripKitUI/documentation/TripKitUI/TKUIRoutingResultsCard":{"abstract":[{"text":"An interactive card for displaying routing results, including updating from\/to location, time and selected modes.","type":"text"}],"fragments":[{"text":"class","kind":"keyword"},{"text":" ","kind":"text"},{"text":"TKUIRoutingResultsCard","kind":"identifier"}],"role":"symbol","url":"\/documentation\/tripkitui\/tkuiroutingresultscard","identifier":"doc:\/\/TripKitUI\/documentation\/TripKitUI\/TKUIRoutingResultsCard","type":"topic","title":"TKUIRoutingResultsCard","kind":"symbol","navigatorTitle":[{"text":"TKUIRoutingResultsCard","kind":"identifier"}]},"doc://TripKitUI/documentation/TripKitUI/TKUIRoutingResultsCard/CustomItem":{"navigatorTitle":[{"text":"CustomItem","kind":"identifier"}],"type":"topic","identifier":"doc:\/\/TripKitUI\/documentation\/TripKitUI\/TKUIRoutingResultsCard\/CustomItem","abstract":[],"fragments":[{"text":"struct","kind":"keyword"},{"text":" ","kind":"text"},{"text":"CustomItem","kind":"identifier"}],"kind":"symbol","role":"symbol","url":"\/documentation\/tripkitui\/tkuiroutingresultscard\/customitem","title":"TKUIRoutingResultsCard.CustomItem"},"doc://TripKitUI/objc(pl)UIResponderStandardEditActions":{"type":"unresolvable","identifier":"doc:\/\/TripKitUI\/objc(pl)UIResponderStandardEditActions","title":"UIKit.UIResponderStandardEditActions"},"doc://TripKitUI/documentation/TripKitUI/TKUIRoutingResultsCard/willDisappear(animated:)":{"type":"topic","identifier":"doc:\/\/TripKitUI\/documentation\/TripKitUI\/TKUIRoutingResultsCard\/willDisappear(animated:)","title":"willDisappear(animated:)","role":"symbol","url":"\/documentation\/tripkitui\/tkuiroutingresultscard\/willdisappear(animated:)","fragments":[{"kind":"keyword","text":"func"},{"kind":"text","text":" "},{"kind":"identifier","text":"willDisappear"},{"kind":"text","text":"("},{"kind":"externalParam","text":"animated"},{"kind":"text","text":": "},{"kind":"typeIdentifier","text":"Bool","preciseIdentifier":"s:Sb"},{"kind":"text","text":")"}],"kind":"symbol","abstract":[]},"doc://TripKitUI/documentation/TripKitUI/TKUITripOverviewViewController":{"title":"TKUITripOverviewViewController","identifier":"doc:\/\/TripKitUI\/documentation\/TripKitUI\/TKUITripOverviewViewController","fragments":[{"kind":"keyword","text":"class"},{"kind":"text","text":" "},{"kind":"identifier","text":"TKUITripOverviewViewController"}],"url":"\/documentation\/tripkitui\/tkuitripoverviewviewcontroller","role":"symbol","abstract":[{"type":"text","text":"The "},{"type":"codeVoice","code":"TKUITripOverviewViewController"},{"type":"text","text":" class provides a user interface for viewing a individual trip."}],"kind":"symbol","type":"topic","navigatorTitle":[{"kind":"identifier","text":"TKUITripOverviewViewController"}]},"doc://TripKitUI/documentation/TripKitUI/TKUIRoutingResultsCard/refreshForUpdatedModes()":{"url":"\/documentation\/tripkitui\/tkuiroutingresultscard\/refreshforupdatedmodes()","abstract":[],"identifier":"doc:\/\/TripKitUI\/documentation\/TripKitUI\/TKUIRoutingResultsCard\/refreshForUpdatedModes()","type":"topic","role":"symbol","title":"refreshForUpdatedModes()","fragments":[{"text":"func","kind":"keyword"},{"text":" ","kind":"text"},{"text":"refreshForUpdatedModes","kind":"identifier"},{"text":"()","kind":"text"}],"kind":"symbol"},"doc://TripKitUI/documentation/TripKitUI/TKUIRoutingResultsCard/traitCollectionDidChange(_:)":{"kind":"symbol","identifier":"doc:\/\/TripKitUI\/documentation\/TripKitUI\/TKUIRoutingResultsCard\/traitCollectionDidChange(_:)","url":"\/documentation\/tripkitui\/tkuiroutingresultscard\/traitcollectiondidchange(_:)","role":"symbol","title":"traitCollectionDidChange(_:)","abstract":[],"type":"topic","fragments":[{"kind":"keyword","text":"func"},{"kind":"text","text":" "},{"kind":"identifier","text":"traitCollectionDidChange"},{"kind":"text","text":"("},{"preciseIdentifier":"c:objc(cs)UITraitCollection","kind":"typeIdentifier","text":"UITraitCollection"},{"kind":"text","text":"?)"}]},"doc://TripKitUI/7RxSwift18ReactiveCompatibleP":{"type":"unresolvable","identifier":"doc:\/\/TripKitUI\/7RxSwift18ReactiveCompatibleP","title":"RxSwift.ReactiveCompatible"},"doc://TripKitUI/documentation/TripKitUI/TKUIRoutingResultsCard/didAppear(animated:)":{"identifier":"doc:\/\/TripKitUI\/documentation\/TripKitUI\/TKUIRoutingResultsCard\/didAppear(animated:)","title":"didAppear(animated:)","abstract":[],"type":"topic","role":"symbol","fragments":[{"text":"func","kind":"keyword"},{"text":" ","kind":"text"},{"text":"didAppear","kind":"identifier"},{"text":"(","kind":"text"},{"text":"animated","kind":"externalParam"},{"text":": ","kind":"text"},{"text":"Bool","preciseIdentifier":"s:Sb","kind":"typeIdentifier"},{"text":")","kind":"text"}],"kind":"symbol","url":"\/documentation\/tripkitui\/tkuiroutingresultscard\/didappear(animated:)"},"doc://TripKitUI/documentation/TripKitUI/TKUIRoutingResultsCard/TripGroupAction":{"navigatorTitle":[{"text":"TripGroupAction","kind":"identifier"}],"kind":"symbol","fragments":[{"text":"typealias","kind":"keyword"},{"text":" ","kind":"text"},{"text":"TripGroupAction","kind":"identifier"}],"identifier":"doc:\/\/TripKitUI\/documentation\/TripKitUI\/TKUIRoutingResultsCard\/TripGroupAction","url":"\/documentation\/tripkitui\/tkuiroutingresultscard\/tripgroupaction","title":"TKUIRoutingResultsCard.TripGroupAction","role":"symbol","type":"topic","abstract":[]},"doc://TripKitUI/documentation/TripKitUI/TKUIRoutingResultsCard/TKUIRoutingQueryInputCardDelegate-Implementations":{"identifier":"doc:\/\/TripKitUI\/documentation\/TripKitUI\/TKUIRoutingResultsCard\/TKUIRoutingQueryInputCardDelegate-Implementations","url":"\/documentation\/tripkitui\/tkuiroutingresultscard\/tkuiroutingqueryinputcarddelegate-implementations","title":"TKUIRoutingQueryInputCardDelegate Implementations","type":"topic","kind":"article","role":"collectionGroup","abstract":[]},"doc://TripKitUI/documentation/TripKitUI/TKUITripModeByModeViewController":{"abstract":[],"identifier":"doc:\/\/TripKitUI\/documentation\/TripKitUI\/TKUITripModeByModeViewController","role":"symbol","type":"topic","navigatorTitle":[{"text":"TKUITripModeByModeViewController","kind":"identifier"}],"fragments":[{"text":"class","kind":"keyword"},{"text":" ","kind":"text"},{"text":"TKUITripModeByModeViewController","kind":"identifier"}],"kind":"symbol","url":"\/documentation\/tripkitui\/tkuitripmodebymodeviewcontroller","title":"TKUITripModeByModeViewController"},"doc://TripKitUI/documentation/TripKitUI":{"type":"topic","identifier":"doc:\/\/TripKitUI\/documentation\/TripKitUI","role":"collection","kind":"symbol","abstract":[{"type":"text","text":"User interface framework providing pre-built view controllers and UI components for transportation applications."}],"url":"\/documentation\/tripkitui","title":"TripKitUI"},"doc://TripKitUI/s16SendableMetatypeP":{"type":"unresolvable","identifier":"doc:\/\/TripKitUI\/s16SendableMetatypeP","title":"Swift.SendableMetatype"},"doc://TripKitUI/documentation/TripKitUI/TKUIRoutingResultsCard/config":{"url":"\/documentation\/tripkitui\/tkuiroutingresultscard\/config","kind":"symbol","type":"topic","identifier":"doc:\/\/TripKitUI\/documentation\/TripKitUI\/TKUIRoutingResultsCard\/config","fragments":[{"text":"static","kind":"keyword"},{"text":" ","kind":"text"},{"text":"var","kind":"keyword"},{"text":" ","kind":"text"},{"text":"config","kind":"identifier"},{"text":": ","kind":"text"},{"preciseIdentifier":"c:@M@TripKitUI@objc(cs)TKUIRoutingResultsCard","text":"TKUIRoutingResultsCard","kind":"typeIdentifier"},{"text":".","kind":"text"},{"preciseIdentifier":"s:9TripKitUI22TKUIRoutingResultsCardC13ConfigurationV","text":"Configuration","kind":"typeIdentifier"}],"title":"config","abstract":[],"role":"symbol"},"doc://TripKitUI/documentation/TripKitUI/TKUIRoutingResultsCard/init(destination:origin:zoomToDestination:initialPosition:)":{"role":"symbol","abstract":[{"text":"Initializes and returns a newly allocated card showing results of routing from current","type":"text"},{"text":" ","type":"text"},{"text":"location to a specified destination. The card will be placed at the specified initial","type":"text"},{"text":" ","type":"text"},{"text":"position.","type":"text"}],"type":"topic","title":"init(destination:origin:zoomToDestination:initialPosition:)","kind":"symbol","fragments":[{"kind":"identifier","text":"init"},{"kind":"text","text":"("},{"kind":"externalParam","text":"destination"},{"kind":"text","text":": "},{"kind":"typeIdentifier","preciseIdentifier":"c:objc(pl)MKAnnotation","text":"MKAnnotation"},{"kind":"text","text":", "},{"kind":"externalParam","text":"origin"},{"kind":"text","text":": "},{"kind":"typeIdentifier","preciseIdentifier":"c:objc(pl)MKAnnotation","text":"MKAnnotation"},{"kind":"text","text":"?, "},{"kind":"externalParam","text":"zoomToDestination"},{"kind":"text","text":": "},{"kind":"typeIdentifier","preciseIdentifier":"s:Sb","text":"Bool"},{"kind":"text","text":", "},{"kind":"externalParam","text":"initialPosition"},{"kind":"text","text":": "},{"kind":"typeIdentifier","preciseIdentifier":"s:20TGCardViewController0A8PositionO","text":"TGCardPosition"},{"kind":"text","text":"?)"}],"url":"\/documentation\/tripkitui\/tkuiroutingresultscard\/init(destination:origin:zoomtodestination:initialposition:)","identifier":"doc:\/\/TripKitUI\/documentation\/TripKitUI\/TKUIRoutingResultsCard\/init(destination:origin:zoomToDestination:initialPosition:)"},"doc://TripKitUI/s28CustomDebugStringConvertibleP":{"identifier":"doc:\/\/TripKitUI\/s28CustomDebugStringConvertibleP","type":"unresolvable","title":"Swift.CustomDebugStringConvertible"},"doc://TripKitUI/objc(pl)UIScrollViewDelegate":{"type":"unresolvable","identifier":"doc:\/\/TripKitUI\/objc(pl)UIScrollViewDelegate","title":"UIKit.UIScrollViewDelegate"},"doc://TripKitUI/objc(pl)UITableViewDelegate":{"identifier":"doc:\/\/TripKitUI\/objc(pl)UITableViewDelegate","type":"unresolvable","title":"UIKit.UITableViewDelegate"},"doc://TripKitUI/documentation/TripKitUI/TKUIRoutingResultsCard/Configuration":{"fragments":[{"text":"struct","kind":"keyword"},{"text":" ","kind":"text"},{"text":"Configuration","kind":"identifier"}],"abstract":[{"type":"text","text":"Configuration of any "},{"type":"codeVoice","code":"TKUIRoutingResultsCard"},{"type":"text","text":"."}],"title":"TKUIRoutingResultsCard.Configuration","identifier":"doc:\/\/TripKitUI\/documentation\/TripKitUI\/TKUIRoutingResultsCard\/Configuration","role":"symbol","navigatorTitle":[{"text":"Configuration","kind":"identifier"}],"url":"\/documentation\/tripkitui\/tkuiroutingresultscard\/configuration","type":"topic","kind":"symbol"},"doc://TripKitUI/documentation/TripKitUI/TKUIRoutingResultsCard/init(request:editable:modes:)":{"fragments":[{"text":"init","kind":"identifier"},{"text":"(","kind":"text"},{"text":"request","kind":"externalParam"},{"text":": ","kind":"text"},{"preciseIdentifier":"c:@M@TripKit@objc(cs)TripRequest","text":"TripRequest","kind":"typeIdentifier"},{"text":", ","kind":"text"},{"text":"editable","kind":"externalParam"},{"text":": ","kind":"text"},{"preciseIdentifier":"s:Sb","text":"Bool","kind":"typeIdentifier"},{"text":", ","kind":"text"},{"text":"modes","kind":"externalParam"},{"text":": ","kind":"text"},{"preciseIdentifier":"s:Sh","text":"Set","kind":"typeIdentifier"},{"text":"<","kind":"text"},{"preciseIdentifier":"s:SS","text":"String","kind":"typeIdentifier"},{"text":">?)","kind":"text"}],"url":"\/documentation\/tripkitui\/tkuiroutingresultscard\/init(request:editable:modes:)","identifier":"doc:\/\/TripKitUI\/documentation\/TripKitUI\/TKUIRoutingResultsCard\/init(request:editable:modes:)","role":"symbol","title":"init(request:editable:modes:)","kind":"symbol","abstract":[{"type":"text","text":"Initializes and returns a newly allocated card showing results for a specific routing request."}],"type":"topic"},"doc://TripKitUI/documentation/TripKitUI/TKUIRoutingResultsCard/canPerformAction(_:withSender:)":{"abstract":[],"title":"canPerformAction(_:withSender:)","fragments":[{"kind":"keyword","text":"func"},{"kind":"text","text":" "},{"kind":"identifier","text":"canPerformAction"},{"kind":"text","text":"("},{"preciseIdentifier":"s:10ObjectiveC8SelectorV","kind":"typeIdentifier","text":"Selector"},{"kind":"text","text":", "},{"kind":"externalParam","text":"withSender"},{"kind":"text","text":": "},{"kind":"keyword","text":"Any"},{"kind":"text","text":"?) -> "},{"preciseIdentifier":"s:Sb","kind":"typeIdentifier","text":"Bool"}],"url":"\/documentation\/tripkitui\/tkuiroutingresultscard\/canperformaction(_:withsender:)","identifier":"doc:\/\/TripKitUI\/documentation\/TripKitUI\/TKUIRoutingResultsCard\/canPerformAction(_:withSender:)","kind":"symbol","role":"symbol","type":"topic"},"doc://TripKitUI/documentation/TripKitUI/TKUITripModeByModeCard":{"fragments":[{"kind":"keyword","text":"class"},{"kind":"text","text":" "},{"kind":"identifier","text":"TKUITripModeByModeCard"}],"abstract":[],"url":"\/documentation\/tripkitui\/tkuitripmodebymodecard","role":"symbol","identifier":"doc:\/\/TripKitUI\/documentation\/TripKitUI\/TKUITripModeByModeCard","title":"TKUITripModeByModeCard","navigatorTitle":[{"kind":"identifier","text":"TKUITripModeByModeCard"}],"kind":"symbol","type":"topic"},"doc://TripKitUI/documentation/TripKitUI/TKUIRoutingResultsCard/willAppear(animated:)":{"title":"willAppear(animated:)","url":"\/documentation\/tripkitui\/tkuiroutingresultscard\/willappear(animated:)","role":"symbol","fragments":[{"text":"func","kind":"keyword"},{"text":" ","kind":"text"},{"text":"willAppear","kind":"identifier"},{"text":"(","kind":"text"},{"text":"animated","kind":"externalParam"},{"text":": ","kind":"text"},{"preciseIdentifier":"s:Sb","text":"Bool","kind":"typeIdentifier"},{"text":")","kind":"text"}],"kind":"symbol","abstract":[],"identifier":"doc:\/\/TripKitUI\/documentation\/TripKitUI\/TKUIRoutingResultsCard\/willAppear(animated:)","type":"topic"},"doc://TripKitUI/documentation/TripKitUI/TKUIRoutingResultsCard/keyCommands":{"identifier":"doc:\/\/TripKitUI\/documentation\/TripKitUI\/TKUIRoutingResultsCard\/keyCommands","fragments":[{"kind":"keyword","text":"var"},{"kind":"text","text":" "},{"kind":"identifier","text":"keyCommands"},{"kind":"text","text":": ["},{"kind":"typeIdentifier","preciseIdentifier":"c:objc(cs)UIKeyCommand","text":"UIKeyCommand"},{"kind":"text","text":"]?"}],"url":"\/documentation\/tripkitui\/tkuiroutingresultscard\/keycommands","kind":"symbol","title":"keyCommands","type":"topic","role":"symbol","abstract":[]},"doc://TripKitUI/documentation/TripKitUI/TKUIRoutingResultsCard/onSelection":{"type":"topic","identifier":"doc:\/\/TripKitUI\/documentation\/TripKitUI\/TKUIRoutingResultsCard\/onSelection","abstract":[{"text":"Set this callback to provide a custom handler for what should happen when a user selects a trip.","type":"text"}],"url":"\/documentation\/tripkitui\/tkuiroutingresultscard\/onselection","title":"onSelection","fragments":[{"kind":"keyword","text":"var"},{"kind":"text","text":" "},{"kind":"identifier","text":"onSelection"},{"kind":"text","text":": (("},{"kind":"typeIdentifier","text":"Trip","preciseIdentifier":"c:@M@TripKit@objc(cs)Trip"},{"kind":"text","text":") -> "},{"kind":"typeIdentifier","text":"Bool","preciseIdentifier":"s:Sb"},{"kind":"text","text":")?"}],"kind":"symbol","role":"symbol"},"doc://TripKitUI/objc(pl)UIUserActivityRestoring":{"title":"UIKit.UIUserActivityRestoring","identifier":"doc:\/\/TripKitUI\/objc(pl)UIUserActivityRestoring","type":"unresolvable"},"doc://TripKitUI/s8CopyableP":{"type":"unresolvable","identifier":"doc:\/\/TripKitUI\/s8CopyableP","title":"Swift.Copyable"},"doc://TripKitUI/20TGCardViewController013TGPreferrableB0P":{"title":"TGCardViewController.TGPreferrableView","identifier":"doc:\/\/TripKitUI\/20TGCardViewController013TGPreferrableB0P","type":"unresolvable"},"doc://TripKitUI/documentation/TripKitUI/TKUIRoutingResultsViewController":{"abstract":[{"type":"text","text":"The "},{"type":"codeVoice","code":"TKUIRoutingResultsViewController"},{"type":"text","text":" class provides a user interface for viewing"},{"type":"text","text":" "},{"type":"text","text":"routing options."}],"type":"topic","role":"symbol","url":"\/documentation\/tripkitui\/tkuiroutingresultsviewcontroller","identifier":"doc:\/\/TripKitUI\/documentation\/TripKitUI\/TKUIRoutingResultsViewController","title":"TKUIRoutingResultsViewController","fragments":[{"text":"class","kind":"keyword"},{"text":" ","kind":"text"},{"text":"TKUIRoutingResultsViewController","kind":"identifier"}],"navigatorTitle":[{"text":"TKUIRoutingResultsViewController","kind":"identifier"}],"kind":"symbol"},"doc://TripKitUI/s23CustomStringConvertibleP":{"type":"unresolvable","identifier":"doc:\/\/TripKitUI\/s23CustomStringConvertibleP","title":"Swift.CustomStringConvertible"},"doc://TripKitUI/s7CVarArgP":{"title":"Swift.CVarArg","identifier":"doc:\/\/TripKitUI\/s7CVarArgP","type":"unresolvable"},"doc://TripKitUI/documentation/TripKitUI/TKUIRoutingResultsCardDelegate":{"url":"\/documentation\/tripkitui\/tkuiroutingresultscarddelegate","type":"topic","navigatorTitle":[{"kind":"identifier","text":"TKUIRoutingResultsCardDelegate"}],"fragments":[{"kind":"keyword","text":"protocol"},{"kind":"text","text":" "},{"kind":"identifier","text":"TKUIRoutingResultsCardDelegate"}],"title":"TKUIRoutingResultsCardDelegate","role":"symbol","abstract":[],"kind":"symbol","identifier":"doc:\/\/TripKitUI\/documentation\/TripKitUI\/TKUIRoutingResultsCardDelegate"},"doc://TripKitUI/documentation/TripKitUI/TKUIRoutingResultsViewControllerDelegate":{"url":"\/documentation\/tripkitui\/tkuiroutingresultsviewcontrollerdelegate","kind":"symbol","fragments":[{"kind":"keyword","text":"protocol"},{"kind":"text","text":" "},{"kind":"identifier","text":"TKUIRoutingResultsViewControllerDelegate"}],"navigatorTitle":[{"kind":"identifier","text":"TKUIRoutingResultsViewControllerDelegate"}],"title":"TKUIRoutingResultsViewControllerDelegate","identifier":"doc:\/\/TripKitUI\/documentation\/TripKitUI\/TKUIRoutingResultsViewControllerDelegate","abstract":[],"type":"topic","role":"symbol"}}}